nbeats/__init__.py
nbeats/forecasting_nbeats.py
nbeats/contrib/__init__.py
nbeats/contrib/nbeatsx/__init__.py
nbeats/contrib/nbeatsx/nbeatsx.py
nbeats/contrib/nbeatsx/nbeatsx_model.py
nbeats/contrib/utils/__init__.py
nbeats/contrib/utils/numpy/__init__.py
nbeats/contrib/utils/numpy/metrics.py
nbeats/contrib/utils/pytorch/__init__.py
nbeats/contrib/utils/pytorch/losses.py
nbeats/contrib/utils/pytorch/sampler.py
d3m_nbeats-0.1.0.dist-info/LICENSE
d3m_nbeats-0.1.0.dist-info/METADATA
d3m_nbeats-0.1.0.dist-info/WHEEL
d3m_nbeats-0.1.0.dist-info/entry_points.txt
d3m_nbeats-0.1.0.dist-info/top_level.txt
d3m_nbeats-0.1.0.dist-info/RECORD
