Metadata-Version: 2.1
Name: d3m-nbeats
Version: 0.1.0
Summary: NBEATS implementation for Data Driven Discovery(D3M) Time Series Forecasting
Home-page: https://github.com/autonlab/nbeats
Author: CMU
Author-email: awillia2@andrew.cmu.edu
License: MIT
Platform: UNKNOWN
License-File: LICENSE
Requires-Dist: d3m
Requires-Dist: numpy
Requires-Dist: pandas
Requires-Dist: scipy
Requires-Dist: torch (>=1.3.1)
